aio/__init__.py
aio_llm/__init__.py
aiollm-0.0.1.dist-info/METADATA
aiollm-0.0.1.dist-info/WHEEL
aiollm-0.0.1.dist-info/top_level.txt
aiollm-0.0.1.dist-info/RECORD
