Metadata-Version: 2.4
Name: aiollm
Version: 0.0.1
Summary: Async utilities and LLM integrations
Author: BAEM1N
